prompt_for_password/__init__.py
prompt_for_password/prompt_for_password.py
prompt_for_password-1.0.4.dist-info/AUTHORS.rst
prompt_for_password-1.0.4.dist-info/LICENSE
prompt_for_password-1.0.4.dist-info/METADATA
prompt_for_password-1.0.4.dist-info/WHEEL
prompt_for_password-1.0.4.dist-info/entry_points.txt
prompt_for_password-1.0.4.dist-info/top_level.txt
prompt_for_password-1.0.4.dist-info/RECORD
