Metadata-Version: 2.1
Name: prompt-for-password
Version: 1.0.4
Summary: Script which securely prompts for a password and outputs it to stdout
Home-page: https://github.com/apiology/prompt_for_password
Author: Vince Broz
Author-email: vince@broz.cc
License: MIT license
Keywords: prompt_for_password
Platform: UNKNOWN
Classifier: Development Status :: 2 - Pre-Alpha
Classifier: Intended Audience :: Developers
Classifier: License :: OSI Approved :: MIT License
Classifier: Natural Language :: English
Classifier: Programming Language :: Python :: 3
Classifier: Programming Language :: Python :: 3.6
Classifier: Programming Language :: Python :: 3.7
Classifier: Programming Language :: Python :: 3.8
Classifier: Programming Language :: Python :: 3.9
Requires-Python: >=3.6
Requires-Dist: pysectools
